README.rst
ez_setup.py
setup.py
mangoutils/__init__.py
mangoutils/version.py
mangoutils.egg-info/PKG-INFO
mangoutils.egg-info/SOURCES.txt
mangoutils.egg-info/dependency_links.txt
mangoutils.egg-info/top_level.txt
mangoutils/html/__init__.py
mangoutils/html/parser.py
mangoutils/system/__init__.py
mangoutils/system/common.py
mangoutils/web/__init__.py
mangoutils/web/cdns.py
mangoutils/web/tlds.py
mangoutils/web/update_cdns.py
mangoutils/web/update_tlds.py
mangoutils/web/urls.py