Metadata-Version: 1.1
Name: mangoutils
Version: 1.0.1
Summary: A collection of commonly useful utilities.
Home-page: http://pypi.python.org/pypi/mangoutils/
Author: Amol Umrale
Author-email: babaiscool@gmail.com
License: UNKNOWN
Platform: UNKNOWN
Classifier: Development Status :: 4 - Beta
Classifier: License :: OSI Approved :: MIT License
Classifier: Natural Language :: English
Classifier: Operating System :: POSIX :: Linux
Classifier: Operating System :: Microsoft :: Windows
